django_token_bucket/__init__.py
django_token_bucket/admin.py
django_token_bucket/apps.py
django_token_bucket/models.py
django_token_bucket/migrations/0001_initial.py
django_token_bucket/migrations/0002_auto_20191216_1228.py
django_token_bucket/migrations/0003_auto_20200111_1625.py
django_token_bucket/migrations/0004_auto_20200111_1625.py
django_token_bucket/migrations/__init__.py
django_token_bucket-0.2.4.dist-info/LICENSE
django_token_bucket-0.2.4.dist-info/METADATA
django_token_bucket-0.2.4.dist-info/WHEEL
django_token_bucket-0.2.4.dist-info/top_level.txt
django_token_bucket-0.2.4.dist-info/RECORD
