Metadata-Version: 2.1
Name: django-token-bucket
Version: 0.2.4
Summary: Django Tocken Bucket support.
Home-page: https://github.com/fsinfuhh/django_token_bucket
Author: Nils Rokita, Henning Pridöhl
Author-email: github@rokita.it
Maintainer: Nils Rokita
Maintainer-email: github@rokita.it
License: License :: OSI Approved :: MIT License
Platform: UNKNOWN
Classifier: Development Status :: 4 - Beta
Classifier: Environment :: Web Environment
Classifier: Programming Language :: Python
Classifier: License :: OSI Approved :: MIT License
Classifier: Operating System :: OS Independent
Classifier: Intended Audience :: Developers
Classifier: Topic :: Software Development :: Libraries :: Python Modules
Classifier: Programming Language :: Python :: 3
Classifier: Programming Language :: Python :: 3.4
Classifier: Programming Language :: Python :: 3.5
Classifier: Programming Language :: Python :: 3.6
Classifier: Programming Language :: Python :: Implementation :: PyPy
Classifier: Programming Language :: Python :: Implementation :: CPython
Classifier: Framework :: Django
License-File: LICENSE
Requires-Dist: Django (>=1.11)
